[{"Date": "2023-05-1", "Minimum temperature (\u00b0C)": "7.3", "Maximum temperature (\u00b0C)": "18.1", "Rainfall (mm)": "0", "Evaporation (mm)": "2.2", "Sunshine (hours)": "3.5", "Speed of maximum wind gust (km/h)": "17", "Time of maximum wind gust": "20:10", "9am Temperature (\u00b0C)": "13.3", "9am relative humidity (%)": "72", "9am cloud amount (oktas)": "7", "9am wind speed (km/h)": 6, "9am MSL pressure (hPa)": "1016.7", "3pm Temperature (\u00b0C)": "17.1", "3pm relative humidity (%)": "54", "3pm cloud amount (oktas)": "7", "3pm wind speed (km/h)": 0, "3pm MSL pressure (hPa)": "1013.9"}, {"Date": "2023-05-2", "Minimum temperature (\u00b0C)": "11.3", "Maximum temperature (\u00b0C)": "20.3", "Rainfall (mm)": "0", "Evaporation (mm)": "2.2", "Sunshine (hours)": "3.6", "Speed of maximum wind gust (km/h)": "35", "Time of maximum wind gust": "14:15", "9am Temperature (\u00b0C)": "13.9", "9am relative humidity (%)": "72", "9am cloud amount (oktas)": "7", "9am wind speed (km/h)": 9, "9am MSL pressure (hPa)": "1015.4", "3pm Temperature (\u00b0C)": "18.4", "3pm relative humidity (%)": "57", "3pm cloud amount (oktas)": "6", "3pm wind speed (km/h)": 7, "3pm MSL pressure (hPa)": "1012.7"}, {"Date": "2023-05-3", "Minimum temperature (\u00b0C)": "11.2", "Maximum temperature (\u00b0C)": "15.7", "Rainfall (mm)": "3.0", "Evaporation (mm)": "4.4", "Sunshine (hours)": "4.2", "Speed of maximum wind gust (km/h)": "44", "Time of maximum wind gust": "06:13", "9am Temperature (\u00b0C)": "13.2", "9am relative humidity (%)": "61", "9am cloud amount (oktas)": "1", "9am wind speed (km/h)": 13, "9am MSL pressure (hPa)": "1011.4", "3pm Temperature (\u00b0C)": "15.2", "3pm relative humidity (%)": "61", "3pm cloud amount (oktas)": "4", "3pm wind speed (km/h)": 13, "3pm MSL pressure (hPa)": "1013.3"}, {"Date": "2023-05-4", "Minimum temperature (\u00b0C)": "8.1", "Maximum temperature (\u00b0C)": "15.6", "Rainfall (mm)": "2.0", "Evaporation (mm)": "1.8", "Sunshine (hours)": "0.5", "Speed of maximum wind gust (km/h)": "19", "Time of maximum wind gust": "23:58", "9am Temperature (\u00b0C)": "10.7", "9am relative humidity (%)": "87", "9am cloud amount (oktas)": "7", "9am wind speed (km/h)": 6, "9am MSL pressure (hPa)": "1022.3", "3pm Temperature (\u00b0C)": "15.3", "3pm relative humidity (%)": "58", "3pm cloud amount (oktas)": "7", "3pm wind speed (km/h)": 2, "3pm MSL pressure (hPa)": "1020.5"}, {"Date": "2023-05-5", "Minimum temperature (\u00b0C)": "10.4", "Maximum temperature (\u00b0C)": "17.9", "Rainfall (mm)": "0", "Evaporation (mm)": "1.6", "Sunshine (hours)": "5.2", "Speed of maximum wind gust (km/h)": "44", "Time of maximum wind gust": "13:11", "9am Temperature (\u00b0C)": "12.4", "9am relative humidity (%)": "62", "9am cloud amount (oktas)": "3", "9am wind speed (km/h)": 15, "9am MSL pressure (hPa)": "1017.2", "3pm Temperature (\u00b0C)": "16.6", "3pm relative humidity (%)": "52", "3pm cloud amount (oktas)": "7", "3pm wind speed (km/h)": 20, "3pm MSL pressure (hPa)": "1013.5"}, {"Date": "2023-05-6", "Minimum temperature (\u00b0C)": "9.8", "Maximum temperature (\u00b0C)": "13.5", "Rainfall (mm)": "14.8", "Evaporation (mm)": "3.8", "Sunshine (hours)": "0.7", "Speed of maximum wind gust (km/h)": "31", "Time of maximum wind gust": "16:13", "9am Temperature (\u00b0C)": "10.0", "9am relative humidity (%)": "95", "9am cloud amount (oktas)": "7", "9am wind speed (km/h)": 0, "9am MSL pressure (hPa)": "1020.3", "3pm Temperature (\u00b0C)": "12.1", "3pm relative humidity (%)": "64", "3pm cloud amount (oktas)": "7", "3pm wind speed (km/h)": 11, "3pm MSL pressure (hPa)": "1019.8"}, {"Date": "2023-05-7", "Minimum temperature (\u00b0C)": "6.6", "Maximum temperature (\u00b0C)": "13.4", "Rainfall (mm)": "22.6", "Evaporation (mm)": "0.6", "Sunshine (hours)": "4.5", "Speed of maximum wind gust (km/h)": "39", "Time of maximum wind gust": "14:00", "9am Temperature (\u00b0C)": "7.4", "9am relative humidity (%)": "88", "9am cloud amount (oktas)": "6", "9am wind speed (km/h)": 11, "9am MSL pressure (hPa)": "1024.4", "3pm Temperature (\u00b0C)": "11.2", "3pm relative humidity (%)": "62", "3pm cloud amount (oktas)": "4", "3pm wind speed (km/h)": 15, "3pm MSL pressure (hPa)": "1024.4"}, {"Date": "2023-05-8", "Minimum temperature (\u00b0C)": "7.4", "Maximum temperature (\u00b0C)": "15.2", "Rainfall (mm)": "5.8", "Evaporation (mm)": "1.6", "Sunshine (hours)": "2.5", "Speed of maximum wind gust (km/h)": "28", "Time of maximum wind gust": "12:53", "9am Temperature (\u00b0C)": "10.0", "9am relative humidity (%)": "82", "9am cloud amount (oktas)": "6", "9am wind speed (km/h)": 6, "9am MSL pressure (hPa)": "1026.4", "3pm Temperature (\u00b0C)": "14.7", "3pm relative humidity (%)": "65", "3pm cloud amount (oktas)": "7", "3pm wind speed (km/h)": 9, "3pm MSL pressure (hPa)": "1023.9"}, {"Date": "2023-05-9", "Minimum temperature (\u00b0C)": "10.0", "Maximum temperature (\u00b0C)": "16.5", "Rainfall (mm)": "1.0", "Evaporation (mm)": "1.8", "Sunshine (hours)": "3.6", "Speed of maximum wind gust (km/h)": "33", "Time of maximum wind gust": "16:20", "9am Temperature (\u00b0C)": "11.3", "9am relative humidity (%)": "91", "9am cloud amount (oktas)": "7", "9am wind speed (km/h)": 4, "9am MSL pressure (hPa)": "1027.3", "3pm Temperature (\u00b0C)": "15.5", "3pm relative humidity (%)": "68", "3pm cloud amount (oktas)": "5", "3pm wind speed (km/h)": 13, "3pm MSL pressure (hPa)": "1026.8"}, {"Date": "2023-05-10", "Minimum temperature (\u00b0C)": "11.2", "Maximum temperature (\u00b0C)": "15.3", "Rainfall (mm)": "1.8", "Evaporation (mm)": "0.8", "Sunshine (hours)": "0.3", "Speed of maximum wind gust (km/h)": "22", "Time of maximum wind gust": "10:54", "9am Temperature (\u00b0C)": "11.5", "9am relative humidity (%)": "95", "9am cloud amount (oktas)": "7", "9am wind speed (km/h)": 6, "9am MSL pressure (hPa)": "1030.1", "3pm Temperature (\u00b0C)": "13.9", "3pm relative humidity (%)": "76", "3pm cloud amount (oktas)": "8", "3pm wind speed (km/h)": 13, "3pm MSL pressure (hPa)": "1028.9"}, {"Date": "2023-05-11", "Minimum temperature (\u00b0C)": "6.8", "Maximum temperature (\u00b0C)": "18.4", "Rainfall (mm)": "0.2", "Evaporation (mm)": "2.2", "Sunshine (hours)": "9.3", "Speed of maximum wind gust (km/h)": "39", "Time of maximum wind gust": "11:43", "9am Temperature (\u00b0C)": "7.7", "9am relative humidity (%)": "100", "9am cloud amount (oktas)": "1", "9am wind speed (km/h)": 9, "9am MSL pressure (hPa)": "1028.6", "3pm Temperature (\u00b0C)": "17.9", "3pm relative humidity (%)": "53", "3pm cloud amount (oktas)": "1", "3pm wind speed (km/h)": 19, "3pm MSL pressure (hPa)": "1024.8"}, {"Date": "2023-05-12", "Minimum temperature (\u00b0C)": "7.7", "Maximum temperature (\u00b0C)": "18.4", "Rainfall (mm)": "0", "Evaporation (mm)": "2.8", "Sunshine (hours)": "5.2", "Speed of maximum wind gust (km/h)": "24", "Time of maximum wind gust": "01:22", "9am Temperature (\u00b0C)": "12.0", "9am relative humidity (%)": "77", "9am cloud amount (oktas)": "7", "9am wind speed (km/h)": 4, "9am MSL pressure (hPa)": "1029.0", "3pm Temperature (\u00b0C)": "16.2", "3pm relative humidity (%)": "64", "3pm cloud amount (oktas)": "7", "3pm wind speed (km/h)": 7, "3pm MSL pressure (hPa)": "1028.7"}, {"Date": "2023-05-13", "Minimum temperature (\u00b0C)": "9.3", "Maximum temperature (\u00b0C)": "16.8", "Rainfall (mm)": "0", "Evaporation (mm)": "1.6", "Sunshine (hours)": "6.4", "Speed of maximum wind gust (km/h)": "19", "Time of maximum wind gust": "15:13", "9am Temperature (\u00b0C)": "10.7", "9am relative humidity (%)": "100", "9am cloud amount (oktas)": "8", "9am wind speed (km/h)": 0, "9am MSL pressure (hPa)": "1032.8", "3pm Temperature (\u00b0C)": "16.4", "3pm relative humidity (%)": "73", "3pm cloud amount (oktas)": "1", "3pm wind speed (km/h)": 9, "3pm MSL pressure (hPa)": "1029.6"}, {"Date": "2023-05-14", "Minimum temperature (\u00b0C)": "7.0", "Maximum temperature (\u00b0C)": "20.7", "Rainfall (mm)": "0", "Evaporation (mm)": "1.8", "Sunshine (hours)": "9.5", "Speed of maximum wind gust (km/h)": "30", "Time of maximum wind gust": "12:11", "9am Temperature (\u00b0C)": "8.2", "9am relative humidity (%)": "100", "9am cloud amount (oktas)": "1", "9am wind speed (km/h)": 7, "9am MSL pressure (hPa)": "1029.9", "3pm Temperature (\u00b0C)": "20.4", "3pm relative humidity (%)": "46", "3pm cloud amount (oktas)": "1", "3pm wind speed (km/h)": 15, "3pm MSL pressure (hPa)": "1025.2"}, {"Date": "2023-05-15", "Minimum temperature (\u00b0C)": "8.2", "Maximum temperature (\u00b0C)": "22.1", "Rainfall (mm)": "0", "Evaporation (mm)": "3.8", "Sunshine (hours)": "9.5", "Speed of maximum wind gust (km/h)": "33", "Time of maximum wind gust": "12:55", "9am Temperature (\u00b0C)": "15.6", "9am relative humidity (%)": "64", "9am cloud amount (oktas)": "1", "9am wind speed (km/h)": 15, "9am MSL pressure (hPa)": "1024.4", "3pm Temperature (\u00b0C)": "21.3", "3pm relative humidity (%)": "41", "3pm cloud amount (oktas)": "1", "3pm wind speed (km/h)": 19, "3pm MSL pressure (hPa)": "1020.4"}, {"Date": "2023-05-16", "Minimum temperature (\u00b0C)": "10.5", "Maximum temperature (\u00b0C)": "13.7", "Rainfall (mm)": "4.0", "Evaporation (mm)": "3.4", "Sunshine (hours)": "0.7", "Speed of maximum wind gust (km/h)": "39", "Time of maximum wind gust": "11:09", "9am Temperature (\u00b0C)": "12.1", "9am relative humidity (%)": "100", "9am cloud amount (oktas)": "7", "9am wind speed (km/h)": 9, "9am MSL pressure (hPa)": "1022.1", "3pm Temperature (\u00b0C)": "13.5", "3pm relative humidity (%)": "62", "3pm cloud amount (oktas)": "7", "3pm wind speed (km/h)": 15, "3pm MSL pressure (hPa)": "1024.7"}, {"Date": "2023-05-17", "Minimum temperature (\u00b0C)": "4.7", "Maximum temperature (\u00b0C)": "14.8", "Rainfall (mm)": "2.6", "Evaporation (mm)": "1.6", "Sunshine (hours)": "9.2", "Speed of maximum wind gust (km/h)": "26", "Time of maximum wind gust": "11:04", "9am Temperature (\u00b0C)": "8.4", "9am relative humidity (%)": "81", "9am cloud amount (oktas)": "1", "9am wind speed (km/h)": 6, "9am MSL pressure (hPa)": "1028.9", "3pm Temperature (\u00b0C)": "14.6", "3pm relative humidity (%)": "45", "3pm cloud amount (oktas)": "3", "3pm wind speed (km/h)": 9, "3pm MSL pressure (hPa)": "1026.1"}, {"Date": "2023-05-18", "Minimum temperature (\u00b0C)": "5.8", "Maximum temperature (\u00b0C)": "13.7", "Rainfall (mm)": "0", "Evaporation (mm)": "1.8", "Sunshine (hours)": "2.0", "Speed of maximum wind gust (km/h)": "22", "Time of maximum wind gust": "12:39", "9am Temperature (\u00b0C)": "7.7", "9am relative humidity (%)": "85", "9am cloud amount (oktas)": "6", "9am wind speed (km/h)": 2, "9am MSL pressure (hPa)": "1026.0", "3pm Temperature (\u00b0C)": "13.5", "3pm relative humidity (%)": "60", "3pm cloud amount (oktas)": "3", "3pm wind speed (km/h)": 9, "3pm MSL pressure (hPa)": "1023.3"}, {"Date": "2023-05-19", "Minimum temperature (\u00b0C)": "5.8", "Maximum temperature (\u00b0C)": "14.6", "Rainfall (mm)": "0", "Evaporation (mm)": "2.0", "Sunshine (hours)": "3.1", "Speed of maximum wind gust (km/h)": "22", "Time of maximum wind gust": "13:49", "9am Temperature (\u00b0C)": "11.3", "9am relative humidity (%)": "81", "9am cloud amount (oktas)": "7", "9am wind speed (km/h)": 2, "9am MSL pressure (hPa)": "1020.5", "3pm Temperature (\u00b0C)": "14.2", "3pm relative humidity (%)": "75", "3pm cloud amount (oktas)": "7", "3pm wind speed (km/h)": 9, "3pm MSL pressure (hPa)": "1017.6"}, {"Date": "2023-05-20", "Minimum temperature (\u00b0C)": "8.7", "Maximum temperature (\u00b0C)": "15.0", "Rainfall (mm)": "2.2", "Evaporation (mm)": "0.4", "Sunshine (hours)": "2.1", "Speed of maximum wind gust (km/h)": "30", "Time of maximum wind gust": "23:49", "9am Temperature (\u00b0C)": "9.5", "9am relative humidity (%)": "86", "9am cloud amount (oktas)": "7", "9am wind speed (km/h)": 7, "9am MSL pressure (hPa)": "1017.3", "3pm Temperature (\u00b0C)": "14.2", "3pm relative humidity (%)": "57", "3pm cloud amount (oktas)": "7", "3pm wind speed (km/h)": 11, "3pm MSL pressure (hPa)": "1014.0"}, {"Date": "2023-05-21", "Minimum temperature (\u00b0C)": "9.2", "Maximum temperature (\u00b0C)": "14.9", "Rainfall (mm)": "1.8", "Evaporation (mm)": "1.8", "Sunshine (hours)": "2.7", "Speed of maximum wind gust (km/h)": "39", "Time of maximum wind gust": "11:23", "9am Temperature (\u00b0C)": "11.5", "9am relative humidity (%)": "96", "9am cloud amount (oktas)": "7", "9am wind speed (km/h)": 9, "9am MSL pressure (hPa)": "1019.2", "3pm Temperature (\u00b0C)": "13.6", "3pm relative humidity (%)": "60", "3pm cloud amount (oktas)": "6", "3pm wind speed (km/h)": 17, "3pm MSL pressure (hPa)": "1023.0"}, {"Date": "2023-05-22", "Minimum temperature (\u00b0C)": "7.7", "Maximum temperature (\u00b0C)": "16.4", "Rainfall (mm)": "0.4", "Evaporation (mm)": "2.0", "Sunshine (hours)": "7.9", "Speed of maximum wind gust (km/h)": "22", "Time of maximum wind gust": "11:45", "9am Temperature (\u00b0C)": "11.4", "9am relative humidity (%)": "72", "9am cloud amount (oktas)": "4", "9am wind speed (km/h)": 4, "9am MSL pressure (hPa)": "1028.6", "3pm Temperature (\u00b0C)": "16.0", "3pm relative humidity (%)": "52", "3pm cloud amount (oktas)": "5", "3pm wind speed (km/h)": 9, "3pm MSL pressure (hPa)": "1026.6"}, {"Date": "2023-05-23", "Minimum temperature (\u00b0C)": "10.2", "Maximum temperature (\u00b0C)": "16.8", "Rainfall (mm)": "0", "Evaporation (mm)": "2.2", "Sunshine (hours)": "7.3", "Speed of maximum wind gust (km/h)": "28", "Time of maximum wind gust": "10:50", "9am Temperature (\u00b0C)": "11.2", "9am relative humidity (%)": "71", "9am cloud amount (oktas)": "6", "9am wind speed (km/h)": 9, "9am MSL pressure (hPa)": "1029.2", "3pm Temperature (\u00b0C)": "16.2", "3pm relative humidity (%)": "52", "3pm cloud amount (oktas)": "7", "3pm wind speed (km/h)": 13, "3pm MSL pressure (hPa)": "1025.8"}, {"Date": "2023-05-24", "Minimum temperature (\u00b0C)": "9.6", "Maximum temperature (\u00b0C)": "15.9", "Rainfall (mm)": "0", "Evaporation (mm)": "2.4", "Sunshine (hours)": "8.0", "Speed of maximum wind gust (km/h)": "46", "Time of maximum wind gust": "14:24", "9am Temperature (\u00b0C)": "10.9", "9am relative humidity (%)": "72", "9am cloud amount (oktas)": "1", "9am wind speed (km/h)": 15, "9am MSL pressure (hPa)": "1026.4", "3pm Temperature (\u00b0C)": "15.6", "3pm relative humidity (%)": "55", "3pm cloud amount (oktas)": "7", "3pm wind speed (km/h)": 26, "3pm MSL pressure (hPa)": "1021.6"}, {"Date": "2023-05-25", "Minimum temperature (\u00b0C)": "10.8", "Maximum temperature (\u00b0C)": "15.0", "Rainfall (mm)": "0", "Evaporation (mm)": "5.2", "Sunshine (hours)": "0.3", "Speed of maximum wind gust (km/h)": "52", "Time of maximum wind gust": "10:43", "9am Temperature (\u00b0C)": "12.6", "9am relative humidity (%)": "55", "9am cloud amount (oktas)": "7", "9am wind speed (km/h)": 22, "9am MSL pressure (hPa)": "1013.1", "3pm Temperature (\u00b0C)": "12.7", "3pm relative humidity (%)": "75", "3pm cloud amount (oktas)": "7", "3pm wind speed (km/h)": 13, "3pm MSL pressure (hPa)": "1010.4"}, {"Date": "2023-05-26", "Minimum temperature (\u00b0C)": "7.6", "Maximum temperature (\u00b0C)": "14.4", "Rainfall (mm)": "2.8", "Evaporation (mm)": "0.2", "Sunshine (hours)": "4.7", "Speed of maximum wind gust (km/h)": "30", "Time of maximum wind gust": "12:55", "9am Temperature (\u00b0C)": "10.0", "9am relative humidity (%)": "70", "9am cloud amount (oktas)": "1", "9am wind speed (km/h)": 9, "9am MSL pressure (hPa)": "1019.1", "3pm Temperature (\u00b0C)": "13.2", "3pm relative humidity (%)": "63", "3pm cloud amount (oktas)": "7", "3pm wind speed (km/h)": 11, "3pm MSL pressure (hPa)": "1018.2"}, {"Date": "2023-05-27", "Minimum temperature (\u00b0C)": "9.8", "Maximum temperature (\u00b0C)": "15.8", "Rainfall (mm)": "0.6", "Evaporation (mm)": "2.4", "Sunshine (hours)": "2.5", "Speed of maximum wind gust (km/h)": "31", "Time of maximum wind gust": "11:58", "9am Temperature (\u00b0C)": "11.5", "9am relative humidity (%)": "68", "9am cloud amount (oktas)": "7", "9am wind speed (km/h)": 13, "9am MSL pressure (hPa)": "1018.2", "3pm Temperature (\u00b0C)": "14.6", "3pm relative humidity (%)": "46", "3pm cloud amount (oktas)": "7", "3pm wind speed (km/h)": 11, "3pm MSL pressure (hPa)": "1015.7"}, {"Date": "2023-05-28", "Minimum temperature (\u00b0C)": "10.9", "Maximum temperature (\u00b0C)": "16.5", "Rainfall (mm)": "6.8", "Evaporation (mm)": "2.8", "Sunshine (hours)": "1.5", "Speed of maximum wind gust (km/h)": "30", "Time of maximum wind gust": "00:36", "9am Temperature (\u00b0C)": "11.4", "9am relative humidity (%)": "92", "9am cloud amount (oktas)": "7", "9am wind speed (km/h)": 15, "9am MSL pressure (hPa)": "1011.5", "3pm Temperature (\u00b0C)": "13.7", "3pm relative humidity (%)": "80", "3pm cloud amount (oktas)": "7", "3pm wind speed (km/h)": 7, "3pm MSL pressure (hPa)": "1010.4"}, {"Date": "2023-05-29", "Minimum temperature (\u00b0C)": "10.0", "Maximum temperature (\u00b0C)": "17.0", "Rainfall (mm)": "5.4", "Evaporation (mm)": "1.0", "Sunshine (hours)": "5.7", "Speed of maximum wind gust (km/h)": "33", "Time of maximum wind gust": "11:31", "9am Temperature (\u00b0C)": "12.8", "9am relative humidity (%)": "72", "9am cloud amount (oktas)": "4", "9am wind speed (km/h)": 13, "9am MSL pressure (hPa)": "1016.5", "3pm Temperature (\u00b0C)": "16.4", "3pm relative humidity (%)": "62", "3pm cloud amount (oktas)": "7", "3pm wind speed (km/h)": 9, "3pm MSL pressure (hPa)": "1016.6"}, {"Date": "2023-05-30", "Minimum temperature (\u00b0C)": "12.7", "Maximum temperature (\u00b0C)": "18.7", "Rainfall (mm)": "0", "Evaporation (mm)": "4.0", "Sunshine (hours)": "2.8", "Speed of maximum wind gust (km/h)": "31", "Time of maximum wind gust": "14:29", "9am Temperature (\u00b0C)": "14.0", "9am relative humidity (%)": "76", "9am cloud amount (oktas)": "7", "9am wind speed (km/h)": 11, "9am MSL pressure (hPa)": "1021.6", "3pm Temperature (\u00b0C)": "17.8", "3pm relative humidity (%)": "64", "3pm cloud amount (oktas)": "6", "3pm wind speed (km/h)": 20, "3pm MSL pressure (hPa)": "1018.9"}, {"Date": "2023-05-31", "Minimum temperature (\u00b0C)": "14.0", "Maximum temperature (\u00b0C)": "17.7", "Rainfall (mm)": "0", "Evaporation (mm)": "2.6", "Sunshine (hours)": "0.4", "Speed of maximum wind gust (km/h)": "44", "Time of maximum wind gust": "17:10", "9am Temperature (\u00b0C)": "16.4", "9am relative humidity (%)": "66", "9am cloud amount (oktas)": "7", "9am wind speed (km/h)": 20, "9am MSL pressure (hPa)": "1016.3", "3pm Temperature (\u00b0C)": "17.4", "3pm relative humidity (%)": "63", "3pm cloud amount (oktas)": "7", "3pm wind speed (km/h)": 17, "3pm MSL pressure (hPa)": "1012.8"}]